server_metrics_apm/__init__.py
server_metrics_apm/client.py
server_metrics_apm/context.py
server_metrics_apm/instrument.py
server_metrics_apm/middleware.py
server_metrics_apm/utils.py
server_metrics_apm-0.1.2.dist-info/METADATA
server_metrics_apm-0.1.2.dist-info/WHEEL
server_metrics_apm-0.1.2.dist-info/top_level.txt
server_metrics_apm-0.1.2.dist-info/RECORD
